logo_plugin/__init__.py
logo_plugin/config.py
logo_plugin/service.py
logo_plugin-0.1.0.dist-info/METADATA
logo_plugin-0.1.0.dist-info/WHEEL
logo_plugin-0.1.0.dist-info/entry_points.txt
logo_plugin-0.1.0.dist-info/top_level.txt
logo_plugin-0.1.0.dist-info/RECORD
