Metadata-Version: 2.4
Name: logo_plugin
Version: 0.1.0
Requires-Dist: requests>=2.25.0
Requires-Dist: pymongo<5.0.0,>=4.0.0
Dynamic: requires-dist
